pycapabilitydecorator/CapabilityDecorator.py
pycapabilitydecorator/__init__.py
pycapabilitydecorator/flasklib.py
pycapabilitydecorator/tools.py
pycapabilitydecorator-0.0.3.dist-info/LICENSE
pycapabilitydecorator-0.0.3.dist-info/METADATA
pycapabilitydecorator-0.0.3.dist-info/WHEEL
pycapabilitydecorator-0.0.3.dist-info/top_level.txt
pycapabilitydecorator-0.0.3.dist-info/RECORD
