Metadata-Version: 2.1
Name: pycapabilitydecorator
Version: 0.0.3
Summary: Python capability decorator for creating modular applications
Author-email: LX <iiixxxiii@qq.com>
License: MIT
Project-URL: Homepage, https://gitee.com/iiixxxiii/py-capability-decorator.git
Requires-Python: >=3.8
License-File: LICENSE
Requires-Dist: click>=8.1.8
Requires-Dist: Flask>=2.3.3
